trilio
