Metadata-Version: 2.1
Name: trilio
Version: 0.1.9
Summary: Trilio is a blockchain written in Python that utilizes the proof-of-work concept and helps creating a more smooth and transparent transaction experience, with multiple integrations such as NFT(s) and tokens. 
Home-page: UNKNOWN
Author: Abdurrahman Ismail Giumale
Author-email: abdxrrahman.ismail@gmail.com
License: MIT
Keywords: python,experimental,blockchain,in-development,token,blockchain-technology,proof-of-work,python-blockchain
Platform: UNKNOWN
Classifier: Development Status :: 5 - Production/Stable
Classifier: Intended Audience :: Education
Classifier: Operating System :: Microsoft :: Windows :: Windows 10
Classifier: License :: OSI Approved :: MIT License
Classifier: Programming Language :: Python :: 3
License-File: LICENSE.txt
